LICENSE.txt
README.md
setup.py
gradio_agents/__init__.py
gradio_agents/analytics.py
gradio_agents/blocks.py
gradio_agents/components.py
gradio_agents/context.py
gradio_agents/data_classes.py
gradio_agents/deprecation.py
gradio_agents/events.py
gradio_agents/exceptions.py
gradio_agents/external.py
gradio_agents/external_utils.py
gradio_agents/flagging.py
gradio_agents/helpers.py
gradio_agents/inputs.py
gradio_agents/interface.py
gradio_agents/interpretation.py
gradio_agents/ipython_ext.py
gradio_agents/layouts.py
gradio_agents/mix.py
gradio_agents/networking.py
gradio_agents/outputs.py
gradio_agents/pipelines.py
gradio_agents/processing_utils.py
gradio_agents/queueing.py
gradio_agents/ranged_response.py
gradio_agents/reload.py
gradio_agents/routes.py
gradio_agents/strings.py
gradio_agents/templates.py
gradio_agents/tunneling.py
gradio_agents/utils.py
gradio_agents.egg-info/PKG-INFO
gradio_agents.egg-info/SOURCES.txt
gradio_agents.egg-info/dependency_links.txt
gradio_agents.egg-info/top_level.txt
gradio_agents/test_data/__init__.py
gradio_agents/test_data/blocks_configs.py
gradio_agents/themes/__init__.py
gradio_agents/themes/app.py
gradio_agents/themes/base.py
gradio_agents/themes/builder_app.py
gradio_agents/themes/default.py
gradio_agents/themes/glass.py
gradio_agents/themes/monochrome.py
gradio_agents/themes/soft.py
gradio_agents/themes/upload_theme.py
gradio_agents/themes/utils/__init__.py
gradio_agents/themes/utils/colors.py
gradio_agents/themes/utils/fonts.py
gradio_agents/themes/utils/readme_content.py
gradio_agents/themes/utils/semver_match.py
gradio_agents/themes/utils/sizes.py
gradio_agents/themes/utils/theme_dropdown.py